{
  "Skills": {
    "sk-1": [
      {
        "skill": {
          "ss-tittle": {
            "text": "React js",
            "tmContent": {
              "summary": "",
              "readMore": "Detalhes",
              "modalContent": "É uma biblioteca de JavaScript para construir interfaces de usuário. Utiliza componentes reutilizáveis para criar aplicações web interativas e dinâmicas.",
              "close": "x"
            }
          },
          "ss-logo": {
            "src": "https://upload.wikimedia.org/wikipedia/commons/thumb/a/a7/React-icon.svg/2300px-React-icon.svg.png",
            "alt": ""
          }
        }
      },
      {
        "skill": {
          "ss-tittle": {
            "text": "Vite",
            "tmContent": {
              "summary": "",
              "readMore": "Detalhes",
              "modalContent": "É uma ferramenta de construção de projetos web para aplicações modernas. Oferece um ambiente de desenvolvimento rápido e eficiente utilizando módulos ES",
              "close": "x"
            }
          },
          "ss-logo": {
            "src": "https://vitejs.dev/logo-with-shadow.png",
            "alt": ""
          }
        }
      },
      {
        "skill": {
          "ss-tittle": {
            "text": "NodeJS",
            "tmContent": {
              "summary": "",
              "readMore": "Detalhes",
              "modalContent": "É um ambiente de execução de JavaScript que permite executar código JavaScript no lado do servidor. É escalável e utilizado para desenvolver aplicações de rede e backend.",
              "close": "x"
            }
          },
          "ss-logo": {
            "src": "https://cdn.freebiesupply.com/logos/large/2x/nodejs-1-logo-png-transparent.png",
            "alt": ""
          }
        }
      },
      {
        "skill": {
          "ss-tittle": {
            "text": "npm",
            "tmContent": {
              "summary": "",
              "readMore": "Detalhes",
              "modalContent": "É o gerenciador de pacotes do Node.js, utilizado para instalar, compartilhar e gerenciar dependências de projetos JavaScript.",
              "close": "x"
            }
          },
          "ss-logo": {
            "src": "https://iconduck.com/vectors/vctr6s6hp3zp/media/svg/download",
            "alt": ""
          }
        }
      },
      {
        "skill": {
          "ss-tittle": {
            "text": "Git",
            "tmContent": {
              "summary": "",
              "readMore": "Detalhes",
              "modalContent": "É um sistema de controle de versões que permite rastrear mudanças em arquivos e colaborar em projetos de desenvolvimento de software. Permite trabalhar em ramificações, mesclar mudanças e manter um histórico de versões.",
              "close": "x"
            }
          },
          "ss-logo": {
            "src": "https://iconduck.com/vectors/vctr6ap2mvtz/media/svg/download",
            "alt": ""
          }
        }
      },
      {
        "skill": {
          "ss-tittle": {
            "text": "GitHub",
            "tmContent": {
              "summary": "",
              "readMore": "Detalhes",
              "modalContent": "É uma plataforma de hospedagem de código que utiliza o Git para controle de versões. Permite que os desenvolvedores colaborem em projetos, revisem código, gerenciem problemas e realizem o acompanhamento de mudanças no código-fonte.",
              "close": "x"
            }
          },
          "ss-logo": {
            "src": "https://static-00.iconduck.com/assets.00/github-icon-512x497-oppthre2.png",
            "alt": ""
          }
        }
      },
      {
        "skill": {
          "ss-tittle": {
            "text": "React Roteador v6",
            "tmContent": {
              "summary": "",
              "readMore": "Detalhes",
              "modalContent": "É uma biblioteca de roteamento para React que permite a navegação entre diferentes componentes de uma aplicação web. A versão 6 introduz uma API simplificada e melhorias na gestão do estado das rotas.",
              "close": "x"
            }
          },
          "ss-logo": {
            "src": "https://iconduck.com/vectors/vctrsmq4rc5x/media/svg/download",
            "alt": ""
          }
        }
      },
      {
        "skill": {
          "ss-tittle": {
            "text": "ReactContext",
            "tmContent": {
              "summary": "",
              "readMore": "Detalhes",
              "modalContent": "É uma característica do React que permite compartilhar dados entre componentes sem precisar passar props manualmente por cada nível da hierarquia. É útil para o gerenciamento do estado global e a gestão de temas em uma aplicação.",
              "close": "x"
            }
          },
          "ss-logo": {
            "src": "https://iconduck.com/vectors/vctrxw3mopo4/media/svg/download",
            "alt": ""
          }
        }
      },
      {
        "skill": {
          "ss-tittle": {
            "text": "Figma",
            "tmContent": {
              "summary": "",
              "readMore": "Detalhes",
              "modalContent": "É uma ferramenta de design de interface de usuário baseada na web que permite aos designers criar protótipos, colaborar em tempo real e projetar interfaces de usuário para aplicações web e móveis.",
              "close": "x"
            }
          },
          "ss-logo": {
            "src": "https://static-00.iconduck.com/assets.00/figma-icon-342x512-hiy4fg6k.png",
            "alt": ""
          }
        }
      },
      {
        "skill": {
          "ss-tittle": {
            "text": "Sass/Scss",
            "tmContent": {
              "summary": "",
              "readMore": "Detalhes",
              "modalContent": "São preprocessadores CSS que estendem a funcionalidade do CSS tradicional, permitindo o uso de variáveis, aninhamento, mixins, entre outras características, para escrever estilos de maneira mais eficiente e modular.",
              "close": "x"
            }
          },
          "ss-logo": {
            "src": "https://static-00.iconduck.com/assets.00/sass-icon-512x512-wrsgqu3t.png",
            "alt": ""
          }
        }
      },
      {
        "skill": {
          "ss-tittle": {
            "text": "CSS do vento favorável",
            "tmContent": {
              "summary": "",
              "readMore": "Detalhes",
              "modalContent": "É um framework de CSS que fornece um conjunto de classes predefinidas para estilizar componentes e criar layouts de maneira rápida e consistente. Baseia-se na filosofia 'utility-first', o que significa que se concentra em fornecer classes utilitárias para estilos específicos em vez de componentes predefinidos.",
              "close": "x"
            }
          },
          "ss-logo": {
            "src": "https://static-00.iconduck.com/assets.00/tailwind-css-icon-512x307-1v56l8ed.png",
            "alt": ""
          }
        }
      },
      {
        "skill": {
          "ss-tittle": {
            "text": "SQL",
            "tmContent": {
              "summary": "",
              "readMore": "Detalhes",
              "modalContent": "SQL, ou Structured Query Language, é uma linguagem de programação utilizada para interagir com bancos de dados relacionais. Permite realizar consultas, inserções, atualizações e exclusões de dados, bem como definir e modificar a estrutura dos bancos de dados. É amplamente utilizado no desenvolvimento de aplicações web e de software para gerenciar e manipular dados de maneira eficiente e segura.",
              "close": "x"
            }
          },
          "ss-logo": {
            "src": "https://static-00.iconduck.com/assets.00/mysql-icon-512x512-26zvphww.png",
            "alt": ""
          }
        }
      }
    ]
  }
}
