{
  "thankYouMessage": "Gracias por enviar tu mensaje!",
  "contactMeta": {
    "title": "“No hay nada más satisfactorio que lograr algo que te dijeron que era imposible.” Si quieres hacer algo bien, puedes intentarlo tú... o llamarme.",
    "email": "tylordeveloper@gmail.com"
  },
  "formFields": {
    "name": {
      "placeholder": "¡No te olvides de tu nombre! (o usa tu apodo, si prefieres ser casual)",
      "label": "Tu Nombre",
      "errorMessage": "¡Ups! Parece que alguien prefiere mantener su identidad en secreto."
    },
    "email": {
      "placeholder": "Escribe tu correo electrónico (preferiblemente uno que revises)",
      "label": "Tu Email",
      "errorMessage": {
        "required": "¿Email? Requerido. Sin él, nos sentimos incompletos.",
        "invalid": "¡Vaya! Parece que el email no es tan válido como pensábamos. Por favor, revisa y corrige."
      }
    },
    "message": {
      "placeholder": "Mensaje (cuéntanos algo interesante... o lo que quieras)",
      "label": "Tu mensaje",
      "errorMessage": "El mensaje está tan vacío como nuestra bandeja de entrada. Por favor, escríbenos algo."
    },
    "submitButton": "Enviar"
  }
}
